pyplatform/reporting/__init__.py
pyplatform/reporting/reporting.py
pyplatform_reporting-2020.12.1.dist-info/METADATA
pyplatform_reporting-2020.12.1.dist-info/WHEEL
pyplatform_reporting-2020.12.1.dist-info/top_level.txt
pyplatform_reporting-2020.12.1.dist-info/RECORD
